biopython_mcp/__init__.py
biopython_mcp/alignment.py
biopython_mcp/database.py
biopython_mcp/phylo.py
biopython_mcp/sequence.py
biopython_mcp/server.py
biopython_mcp/structure.py
biopython_mcp/utils.py
biopython_mcp/modules/__init__.py
biopython_mcp/modules/pubmed.py
biopython_mcp-0.1.8.dist-info/METADATA
biopython_mcp-0.1.8.dist-info/WHEEL
biopython_mcp-0.1.8.dist-info/entry_points.txt
biopython_mcp-0.1.8.dist-info/licenses/LICENSE
biopython_mcp-0.1.8.dist-info/RECORD
