Metadata-Version: 2.4
Name: biopython-mcp
Version: 0.1.8
Summary: Model Context Protocol server providing BioPython library capabilities for biological sequence analysis, alignment, database access, and structural bioinformatics
Project-URL: Homepage, https://github.com/kmaneesh/biopython-mcp
Project-URL: Repository, https://github.com/kmaneesh/biopython-mcp
Project-URL: Documentation, https://github.com/kmaneesh/biopython-mcp/blob/main/docs
Project-URL: Issues, https://github.com/kmaneesh/biopython-mcp/issues
Author-email: Maneesh KUMAR <maneesh.irs@gmail.com>
License: MIT
License-File: LICENSE
Keywords: bioinformatics,biopython,genomics,mcp,model-context-protocol,protein-analysis,sequence-alignment
Classifier: Development Status :: 3 - Alpha
Classifier: Intended Audience :: Developers
Classifier: Intended Audience :: Science/Research
Classifier: License :: OSI Approved :: MIT License
Classifier: Programming Language :: Python :: 3
Classifier: Programming Language :: Python :: 3.10
Classifier: Programming Language :: Python :: 3.11
Classifier: Programming Language :: Python :: 3.12
Classifier: Topic :: Scientific/Engineering :: Bio-Informatics
Classifier: Topic :: Software Development :: Libraries :: Python Modules
Requires-Python: >=3.10
Requires-Dist: biopython>=1.81
Requires-Dist: fastmcp>=0.2.0
Requires-Dist: httpx>=0.25.0
Requires-Dist: mcp>=0.9.0
Requires-Dist: pydantic>=2.0.0
Provides-Extra: dev
Requires-Dist: black>=23.7.0; extra == 'dev'
Requires-Dist: hatchling; extra == 'dev'
Requires-Dist: mypy>=1.5.0; extra == 'dev'
Requires-Dist: pre-commit>=3.3.0; extra == 'dev'
Requires-Dist: pytest-asyncio>=0.21.0; extra == 'dev'
Requires-Dist: pytest-cov>=4.1.0; extra == 'dev'
Requires-Dist: pytest>=7.4.0; extra == 'dev'
Requires-Dist: ruff>=0.1.0; extra == 'dev'
Requires-Dist: types-requests; extra == 'dev'
